KolejkaObserver-0.1.202310121859-nspkg.pth
kolejka/observer/__init__.py
kolejka/observer/__nonpath__.py
kolejka/observer/client.py
kolejka/observer/runner.py
kolejka/observer/server.py
KolejkaObserver-0.1.202310121859.dist-info/METADATA
KolejkaObserver-0.1.202310121859.dist-info/WHEEL
KolejkaObserver-0.1.202310121859.dist-info/entry_points.txt
KolejkaObserver-0.1.202310121859.dist-info/namespace_packages.txt
KolejkaObserver-0.1.202310121859.dist-info/top_level.txt
KolejkaObserver-0.1.202310121859.dist-info/RECORD
